<?xml version="1.0" encoding="utf-8" ?>
<dwsync>
<file name="jamesClassPhoto.PNG" server="gcmw102.palomar.edu//jstephenson3904/" local="132576409860000000" remote="132582499440000000" Dst="1" />
<file name="shrimp tempura.PNG" server="gcmw102.palomar.edu//jstephenson3904/" local="132598006095117466" remote="132598012450000000" Dst="1" />
<file name="imageGallery1.jpg" server="gcmw102.palomar.edu//jstephenson3904/" local="132604012769407582" remote="132606597370000000" Dst="2" />
<file name="imageGallery2.jpg" server="gcmw102.palomar.edu//jstephenson3904/" local="132604013212965388" remote="132606597380000000" Dst="2" />
<file name="imageGallery3.jpg" server="gcmw102.palomar.edu//jstephenson3904/" local="132604013508131722" remote="132606597380000000" Dst="2" />
<file name="imageGallery4.jpeg" server="gcmw102.palomar.edu//jstephenson3904/" local="132604014587118156" remote="132606597380000000" Dst="2" />
<file name="imageGallery5.jpg" server="gcmw102.palomar.edu//jstephenson3904/" local="132604013920670194" remote="132606597380000000" Dst="2" />
<file name="imageGallery6.jpg" server="gcmw102.palomar.edu//jstephenson3904/" local="132604014110714306" remote="132606597390000000" Dst="2" />
<file name="ImageGalleryResampled1.png" server="gcmw102.palomar.edu//jstephenson3904/" local="132609336165724916" remote="132609340140000000" Dst="2" />
<file name="ImageGalleryResampled2.png" server="gcmw102.palomar.edu//jstephenson3904/" local="132609336519938492" remote="132609340150000000" Dst="2" />
<file name="ImageGalleryResampled3.png" server="gcmw102.palomar.edu//jstephenson3904/" local="132609337062251477" remote="132609340150000000" Dst="2" />
<file name="ImageGalleryResampled4.png" server="gcmw102.palomar.edu//jstephenson3904/" local="132609337475011056" remote="132609340150000000" Dst="2" />
<file name="ImageGalleryResampled5.png" server="gcmw102.palomar.edu//jstephenson3904/" local="132609337916265418" remote="132609340150000000" Dst="2" />
<file name="ImageGalleryResampled6.png" server="gcmw102.palomar.edu//jstephenson3904/" local="132609338259145925" remote="132609340160000000" Dst="2" />
<file name="seaSaltResampled.png" server="gcmw102.palomar.edu//jstephenson3904/" local="132610971550589346" remote="132610974400000000" Dst="2" />
<file name="seaSalt.jpg" server="gcmw102.palomar.edu//jstephenson3904/" local="132610970411209533" remote="132610974440000000" Dst="2" />
<file name="ocean.PNG" server="gcmw102.palomar.edu//jstephenson3904/" local="132610947641638327" remote="132610974480000000" Dst="2" />
<file name="valleyImageCropped.png" server="gcmw102.palomar.edu//jstephenson3904/" local="132613616621892502" remote="132614399360000000" Dst="2" />
</dwsync>